lightcurve_pipeline/__init__.py
lightcurve_pipeline/database/__init__.py
lightcurve_pipeline/database/database_interface.py
lightcurve_pipeline/database/update_database.py
lightcurve_pipeline/download/SignStsciRequest.py
lightcurve_pipeline/download/__init__.py
lightcurve_pipeline/ingest/__init__.py
lightcurve_pipeline/ingest/make_lightcurves.py
lightcurve_pipeline/ingest/resolve_target.py
lightcurve_pipeline/quality/__init__.py
lightcurve_pipeline/quality/data_checks.py
lightcurve_pipeline/scripts/__init__.py
lightcurve_pipeline/scripts/build_stats_table.py
lightcurve_pipeline/scripts/download_hstlc.py
lightcurve_pipeline/scripts/ingest_hstlc.py
lightcurve_pipeline/scripts/make_hstlc_plots.py
lightcurve_pipeline/scripts/reset_hstlc_database.py
lightcurve_pipeline/scripts/reset_hstlc_filesystem.py
lightcurve_pipeline/utils/__init__.py
lightcurve_pipeline/utils/periodogram_stats.py
lightcurve_pipeline/utils/targname_dict.py
lightcurve_pipeline/utils/utils.py
lightcurve_pipeline-1.0.data/data/lightcurve_pipeline/utils/config.yaml
lightcurve_pipeline-1.0.data/scripts/build_stats_table
lightcurve_pipeline-1.0.data/scripts/download_hstlc
lightcurve_pipeline-1.0.data/scripts/hstlc_pipeline
lightcurve_pipeline-1.0.data/scripts/ingest_hstlc
lightcurve_pipeline-1.0.data/scripts/make_hstlc_plots
lightcurve_pipeline-1.0.data/scripts/reset_hstlc_database
lightcurve_pipeline-1.0.data/scripts/reset_hstlc_filesystem
lightcurve_pipeline-1.0.dist-info/DESCRIPTION.rst
lightcurve_pipeline-1.0.dist-info/METADATA
lightcurve_pipeline-1.0.dist-info/RECORD
lightcurve_pipeline-1.0.dist-info/WHEEL
lightcurve_pipeline-1.0.dist-info/entry_points.txt
lightcurve_pipeline-1.0.dist-info/metadata.json
lightcurve_pipeline-1.0.dist-info/pbr.json
lightcurve_pipeline-1.0.dist-info/top_level.txt
