Metadata-Version: 2.0
Name: lightcurve-pipeline
Version: 1.0
Summary: Create lightcurves from HST/COS and HST/STIS data
Home-page: https://github.com/justincely/lightcurve_pipeline.git
Author: Matthew Bourque
Author-email: bourque@stsci.edu
License: UNKNOWN
Keywords: astronomy
Platform: UNKNOWN
Classifier: Programming Language :: Python
Classifier: Development Status :: 1 - Planning
Classifier: Intended Audience :: Science/Research
Classifier: Topic :: Scientific/Engineering :: Astronomy
Classifier: Topic :: Scientific/Engineering :: Physics
Classifier: Topic :: Software Development :: Libraries :: Python Modules
Requires: numpy
Requires: scipy
Requires: astropy
Requires: sqlalchemy
Requires: pyyaml
Requires: matplotlib
Requires: bokeh
